zoneramaapi/__init__.py
zoneramaapi/_constants.py
zoneramaapi/async_client.py
zoneramaapi/client.py
zoneramaapi/download_album.py
zoneramaapi/errors.py
zoneramaapi/mixins/account.py
zoneramaapi/mixins/album.py
zoneramaapi/mixins/base.py
zoneramaapi/mixins/photo.py
zoneramaapi/mixins/tab.py
zoneramaapi/mixins/utils.py
zoneramaapi/models/__init__.py
zoneramaapi/models/account.py
zoneramaapi/models/album.py
zoneramaapi/models/aliases.py
zoneramaapi/models/photo.py
zoneramaapi/models/tab.py
zoneramaapi/models/utils.py
zoneramaapi/zeep/async_.py
zoneramaapi/zeep/common.py
zoneramaapi/zeep/sync.py
zoneramaapi-0.4.0.dist-info/licenses/LICENSE
zoneramaapi-0.4.0.dist-info/METADATA
zoneramaapi-0.4.0.dist-info/WHEEL
zoneramaapi-0.4.0.dist-info/top_level.txt
zoneramaapi-0.4.0.dist-info/RECORD
