Metadata-Version: 2.4
Name: zoneramaapi
Version: 0.4.0
Summary: A Python client for the Zonerama API.
Requires-Python: >=3.14
License-File: LICENSE
Requires-Dist: httpx>=0.28.1
Requires-Dist: zeep[async]>=4.3.2
Dynamic: license-file
